Get_Number/__init__.py
Get_Number/test.py
Get_Number-0.0.1.dist-info/LICENSE
Get_Number-0.0.1.dist-info/METADATA
Get_Number-0.0.1.dist-info/WHEEL
Get_Number-0.0.1.dist-info/top_level.txt
Get_Number-0.0.1.dist-info/RECORD
