Metadata-Version: 2.1
Name: Get-Number
Version: 0.0.1
Summary: 获得一些特定数字
Home-page: https://github.com/clodlingxi
Author: ClodLingxi
Author-email: clodlingxi@qq.com
License: UNKNOWN
Platform: UNKNOWN
Classifier: Programming Language :: Python :: 3
Classifier: License :: OSI Approved :: MIT License
Classifier: Operating System :: OS Independent
